qhnswlib.cpython-311-darwin.so
qhnswlib-0.8.6.dist-info/RECORD
qhnswlib-0.8.6.dist-info/WHEEL
qhnswlib-0.8.6.dist-info/top_level.txt
qhnswlib-0.8.6.dist-info/METADATA
qhnswlib-0.8.6.dist-info/licenses/LICENSE
