Metadata-Version: 2.4
Name: qhnswlib
Version: 0.8.6
Summary: HNSW library with int8 quantization support
Home-page: https://github.com/supasearch-ai/qhnswlib
Author: Yury Malkov and others
License-File: LICENSE
Requires-Dist: numpy
Dynamic: author
Dynamic: description
Dynamic: home-page
Dynamic: license-file
Dynamic: requires-dist
Dynamic: summary
